setup.py
SailTestFrame.egg-info/PKG-INFO
SailTestFrame.egg-info/SOURCES.txt
SailTestFrame.egg-info/dependency_links.txt
SailTestFrame.egg-info/entry_points.txt
SailTestFrame.egg-info/not-zip-safe
SailTestFrame.egg-info/requires.txt
SailTestFrame.egg-info/top_level.txt
common/__init__.py
common/customize_error.py
common/data_provider.py
common/html_report.py
common/my_logger.py
common/test_case_finder.py
common/test_decorator.py
common/test_filter.py
common/user_options.py
configs/__init__.py
configs/global_config.py
utilities/__init__.py
utilities/yaml_hepler.py