Metadata-Version: 1.0
Name: SailTestFrame
Version: 0.1
Summary: 搭建个人测试框架模型，实现大部分测试框架功能，可以用于测试前端UI 和 后端接口
Home-page: UNKNOWN
Author: SailYang
Author-email: UNKNOWN
License: MIT
Platform: UNKNOWN
